revgrok/__init__.py
revgrok/client.py
revgrok/configs.py
revgrok/utils.py
revgrok-0.1.5.dist-info/METADATA
revgrok-0.1.5.dist-info/WHEEL
revgrok-0.1.5.dist-info/licenses/LICENSE
revgrok-0.1.5.dist-info/RECORD
