Metadata-Version: 2.4
Name: revgrok
Version: 0.1.5
Summary: This is an unofficial implementation of the grok as api(reverse).
Project-URL: Homepage, https://github.com/linkedlist771/revGrok
Project-URL: Repository, https://github.com/linkedlist771/revGrok.git
Author-email: linkedlist771 <213193509seu@gmail.com>
License-File: LICENSE
Requires-Python: >=3.12
Requires-Dist: build>=1.2.2.post1
Requires-Dist: httpx>=0.28.1
Requires-Dist: twine>=6.1.0
